clerk/app.py
clerk/config.py
clerk/parse.py
josephhaaga_clerk-0.0.12.dist-info/METADATA
josephhaaga_clerk-0.0.12.dist-info/WHEEL
josephhaaga_clerk-0.0.12.dist-info/entry_points.txt
josephhaaga_clerk-0.0.12.dist-info/top_level.txt
josephhaaga_clerk-0.0.12.dist-info/RECORD
