Metadata-Version: 2.1
Name: josephhaaga-clerk
Version: 0.0.12
Summary: A CLI to manage daily journal entries
Home-page: https://github.com/josephhaaga/clerk
Author: Joseph Haaga
Author-email: haaga.joe@gmail.com
Project-URL: Bug Tracker, https://github.com/josephhaaga/clerk/issues
Classifier: Programming Language :: Python :: 3
Classifier: License :: OSI Approved :: MIT License
Classifier: Operating System :: OS Independent
Requires-Python: >=3.8
Requires-Dist: appdirs (==1.4.4)
Requires-Dist: word2number (==1.1)
